{
  "payload": {
    "companyName": "Atlas Dental Clinic",
    "contactName": "Dr. Amine",
    "email": "contact@atlasdental.example",
    "phone": "+212600000000",
    "website": "https://atlasdental.example",
    "market": "Casablanca, Morocco",
    "industry": "healthcare",
    "companySize": "8 staff",
    "problem": "We receive many WhatsApp questions every day and need faster qualification before booking appointments.",
    "channel": "intch",
    "urgency": "this week",
    "budget": "starter",
    "language": "fr"
  },
  "expected": {
    "qualification": "hot",
    "recommendedOffer": "AI WhatsApp Assistant",
    "primaryUseCase": "ai_whatsapp_assistant",
    "detectedIndustry": "healthcare",
    "dataSensitivity": "high",
    "shouldNotify": true
  }
}
